damapper/__init__.py
damapper-1.7.11a2.dist-info/METADATA
damapper-1.7.11a2.dist-info/WHEEL
damapper-1.7.11a2.dist-info/licenses/LICENSE
damapper-1.7.11a2.dist-info/licenses/LICENSES/Apache-2.0.txt
damapper-1.7.11a2.dist-info/RECORD
