Metadata-Version: 2.4
Name: damapper
Version: 1.7.11a2
Summary: DaMapper as a standalone application with UI
License: Apache-2.0
License-File: LICENSE
License-File: LICENSES/Apache-2.0.txt
Keywords: ndt,damage,segmentation,testing,composite
Author: Dienel, Christoph
Maintainer: Garbade, Marc
Maintainer-email: marc.garbade@dlr.de
Requires-Python: >=2.7, !=3.0.*, !=3.1.*, !=3.2.*, !=3.3.*, !=3.4.*
Classifier: Development Status :: 3 - Alpha
Classifier: License :: OSI Approved :: Apache Software License
Classifier: Operating System :: OS Independent
Classifier: Programming Language :: Python :: 2
Classifier: Programming Language :: Python :: 2.7
Classifier: Programming Language :: Python :: 3
Classifier: Programming Language :: Python :: 3.5
Classifier: Programming Language :: Python :: 3.6
Classifier: Programming Language :: Python :: 3.7
Classifier: Programming Language :: Python :: 3.8
Classifier: Programming Language :: Python :: 3.9
Classifier: Programming Language :: Python :: 3.10
Classifier: Programming Language :: Python :: 3.11
Classifier: Programming Language :: Python :: 3.12
Classifier: Programming Language :: Python :: 3.13
Classifier: Programming Language :: Python :: 3.14
Classifier: Topic :: Scientific/Engineering
Requires-Dist: dam-frontend ; (python_version == "2.7" or python_version >= "3.5") and python_version < "4.0" and platform_system == "Windows"
Requires-Dist: dam-python ; python_version >= "3.6" and python_version < "4.0"
Project-URL: Changelog, https://gitlab.com/dlr-sy/damapper/-/blob/dam_release/CHANGELOG.md
Project-URL: Documentation, https://dlr-sy.gitlab.io/damapper
Project-URL: Repository, https://gitlab.com/dlr-sy/damapper
